{
  "main": {
    "id": "891ea38db13138d0",
    "type": "split",
    "children": [
      {
        "id": "736c04f04967e872",
        "type": "tabs",
        "children": [
          {
            "id": "5f2dbacc6a8868c8",
            "type": "leaf",
            "state": {
              "type": "markdown",
              "state": {
                "file": "Android/004.View Binding.md",
                "mode": "source",
                "source": false
              }
            }
          }
        ]
      }
    ],
    "direction": "vertical"
  },
  "left": {
    "id": "a611003181fa4c76",
    "type": "split",
    "children": [
      {
        "id": "7d039d3006bf04f5",
        "type": "tabs",
        "children": [
          {
            "id": "54352ef373609e41",
            "type": "leaf",
            "state": {
              "type": "file-explorer",
              "state": {
                "sortOrder": "alphabetical"
              }
            }
          },
          {
            "id": "d0694e2ee9e14295",
            "type": "leaf",
            "state": {
              "type": "search",
              "state": {
                "query": "",
                "matchingCase": false,
                "explainSearch": false,
                "collapseAll": false,
                "extraContext": false,
                "sortOrder": "alphabetical"
              }
            }
          },
          {
            "id": "04b5c27d1567756a",
            "type": "leaf",
            "state": {
              "type": "starred",
              "state": {}
            }
          }
        ]
      }
    ],
    "direction": "horizontal",
    "width": 300
  },
  "right": {
    "id": "8fba673362f45d1a",
    "type": "split",
    "children": [
      {
        "id": "a93d7c858c8528b0",
        "type": "tabs",
        "children": [
          {
            "id": "e607e66f88474380",
            "type": "leaf",
            "state": {
              "type": "backlink",
              "state": {
                "file": "Android/004.View Binding.md",
                "collapseAll": false,
                "extraContext": false,
                "sortOrder": "alphabetical",
                "showSearch": false,
                "searchQuery": "",
                "backlinkCollapsed": false,
                "unlinkedCollapsed": true
              }
            }
          },
          {
            "id": "33ba87cfdba0761b",
            "type": "leaf",
            "state": {
              "type": "outgoing-link",
              "state": {
                "file": "Android/004.View Binding.md",
                "linksCollapsed": false,
                "unlinkedCollapsed": true
              }
            }
          },
          {
            "id": "0f60852fbfbc5f4c",
            "type": "leaf",
            "state": {
              "type": "tag",
              "state": {
                "sortOrder": "frequency",
                "useHierarchy": true
              }
            }
          },
          {
            "id": "40cee229a019e73d",
            "type": "leaf",
            "state": {
              "type": "outline",
              "state": {
                "file": "Android/004.View Binding.md"
              }
            }
          }
        ]
      }
    ],
    "direction": "horizontal",
    "width": 300,
    "collapsed": true
  },
  "active": "5f2dbacc6a8868c8",
  "lastOpenFiles": [
    "Android/Activity Lifecycle.md",
    "Android/Anko.md",
    "Android/001.WiFi adb.md",
    "Android/004.View Binding.md",
    "Android/003.Activity Lifecycle.md",
    "Android/002.Misc.md",
    "Android/Untitled 45.md",
    "Android/Untitled 43.md",
    "Android/Untitled 44.md",
    "Android/Untitled 42.md"
  ]
}